sensirion_shdlc_sfc5xxx/__init__.py
sensirion_shdlc_sfc5xxx/definitions.py
sensirion_shdlc_sfc5xxx/device.py
sensirion_shdlc_sfc5xxx/device_errors.py
sensirion_shdlc_sfc5xxx/firmware_image.py
sensirion_shdlc_sfc5xxx/types.py
sensirion_shdlc_sfc5xxx/units.py
sensirion_shdlc_sfc5xxx/version.py
sensirion_shdlc_sfc5xxx/commands/__init__.py
sensirion_shdlc_sfc5xxx/commands/activate_calibration.py
sensirion_shdlc_sfc5xxx/commands/advanced_measurements.py
sensirion_shdlc_sfc5xxx/commands/baudrate.py
sensirion_shdlc_sfc5xxx/commands/controller_configuration.py
sensirion_shdlc_sfc5xxx/commands/device_information.py
sensirion_shdlc_sfc5xxx/commands/device_reset.py
sensirion_shdlc_sfc5xxx/commands/factory_reset.py
sensirion_shdlc_sfc5xxx/commands/get_calibration_information.py
sensirion_shdlc_sfc5xxx/commands/get_current_calibration_information.py
sensirion_shdlc_sfc5xxx/commands/get_version.py
sensirion_shdlc_sfc5xxx/commands/medium_unit_configuration.py
sensirion_shdlc_sfc5xxx/commands/read_device_status.py
sensirion_shdlc_sfc5xxx/commands/read_measured_value.py
sensirion_shdlc_sfc5xxx/commands/read_measured_value_buffer.py
sensirion_shdlc_sfc5xxx/commands/reply_delay.py
sensirion_shdlc_sfc5xxx/commands/set_setpoint_and_read_measured_value.py
sensirion_shdlc_sfc5xxx/commands/setpoint.py
sensirion_shdlc_sfc5xxx/commands/setpoint_persist.py
sensirion_shdlc_sfc5xxx/commands/slave_address.py
sensirion_shdlc_sfc5xxx/commands/user_memory_access.py
sensirion_shdlc_sfc5xxx/commands/valve_input_source_configuration.py
sensirion_shdlc_sfc5xxx-0.1.0.dist-info/LICENSE
sensirion_shdlc_sfc5xxx-0.1.0.dist-info/METADATA
sensirion_shdlc_sfc5xxx-0.1.0.dist-info/WHEEL
sensirion_shdlc_sfc5xxx-0.1.0.dist-info/top_level.txt
sensirion_shdlc_sfc5xxx-0.1.0.dist-info/RECORD
