Metadata-Version: 2.1
Name: sensirion-shdlc-sfc5xxx
Version: 0.1.0
Summary: Driver for Communicating With Sensirion SFC5xxx/SFM5xxx
Home-page: https://github.com/sensirion/python-shdlc-sfc5xxx
Author: Urban Bruhin
Author-email: urban.bruhin@sensirion.com
License: BSD
Keywords: sensirion shdlc mass flow controller meter driver mfc mfm sfc5400 sfm5400
Platform: UNKNOWN
Classifier: Intended Audience :: Developers
Classifier: License :: OSI Approved :: BSD License
Classifier: Programming Language :: Python :: 2.7
Classifier: Programming Language :: Python :: 3.5
Classifier: Programming Language :: Python :: 3.6
Classifier: Programming Language :: Python :: 3.7
Classifier: Topic :: System :: Hardware :: Hardware Drivers
Requires-Python: >=2.7, !=3.0.*, !=3.1.*, !=3.2.*, !=3.3.*, !=3.4.*, <4
Requires-Dist: sensirion-shdlc-driver[fwupdate] (~=0.1.5)
Requires-Dist: enum34 ; python_version < "3.4"
Provides-Extra: test
Requires-Dist: flake8 (~=3.6.0) ; extra == 'test'
Requires-Dist: mock (~=3.0.0) ; extra == 'test'
Requires-Dist: pytest (~=3.10.0) ; extra == 'test'
Requires-Dist: pytest-cov (~=2.6.0) ; extra == 'test'
